natural_units/__init__.py
natural_units/base.py
natural_units/core.py
natural_units/gaussian.py
natural_units/geometrized.py
natural_units/hartree_atomic.py
natural_units/hep.py
natural_units/massdimension.py
natural_units/particle_atomic.py
natural_units/plain_hep.py
natural_units/planck.py
natural_units/prefix.py
natural_units/qcd.py
natural_units/si.py
natural_units/stoney.py
natural_units-0.0.2.dist-info/LICENSE
natural_units-0.0.2.dist-info/METADATA
natural_units-0.0.2.dist-info/WHEEL
natural_units-0.0.2.dist-info/top_level.txt
natural_units-0.0.2.dist-info/RECORD
