Metadata-Version: 2.1
Name: natural-units
Version: 0.0.2
Summary: uncertainty quantification for numerical computations
Home-page: https://github.com/APN-Pucky/numcertainties
Author: APN
Author-email: APN-Pucky@no-reply.github.com
Classifier: Programming Language :: Python :: 3
Classifier: License :: OSI Approved :: GNU General Public License v3 (GPLv3)
Classifier: Operating System :: OS Independent
Requires-Python: >=3.6
License-File: LICENSE
Requires-Dist: scipy
Provides-Extra: dev
Requires-Dist: uncertainties ; extra == 'dev'
Requires-Dist: build ; extra == 'dev'
Requires-Dist: pytest ; extra == 'dev'
Requires-Dist: pytest-cov ; extra == 'dev'
Requires-Dist: pytest-profiling ; extra == 'dev'
Requires-Dist: pytest-line-profiler-apn (>=0.1.3) ; extra == 'dev'
Requires-Dist: jupyterlab ; extra == 'dev'
Requires-Dist: pandas ; extra == 'dev'
Requires-Dist: ipython ; extra == 'dev'
Provides-Extra: docs
Requires-Dist: jupyter-sphinx ; extra == 'docs'
Requires-Dist: sphinx-math-dollar ; extra == 'docs'
Requires-Dist: pandoc ; extra == 'docs'
Requires-Dist: sphinx ; extra == 'docs'
Requires-Dist: nbsphinx ; extra == 'docs'
Requires-Dist: sphinx-rtd-theme ; extra == 'docs'
Requires-Dist: numpydoc ; extra == 'docs'
Requires-Dist: sphinx-autobuild ; extra == 'docs'
